pythonfiledatastore/__init__.py
pythonfiledatastore/main_executor.py
pythonfiledatastore/mock_unit.py
pythonfiledatastore/operations.py
pythonfiledatastore-1.5.dist-info/METADATA
pythonfiledatastore-1.5.dist-info/WHEEL
pythonfiledatastore-1.5.dist-info/top_level.txt
pythonfiledatastore-1.5.dist-info/RECORD
