Metadata-Version: 2.1
Name: pythonfiledatastore
Version: 1.5
Summary: File based datastore
Home-page: https://github.com/njaveed/Datastore.git
Author: Javeed
Author-email: meetjaveed11@gmail.com
License: MIT
Platform: UNKNOWN
Classifier: Programming Language :: Python :: 3
Classifier: License :: OSI Approved :: MIT License
Classifier: Operating System :: OS Independent
Requires-Python: >=3.6
Requires-Dist: cachetools
